setup.py
distributionsMM/Binomialdistribution.py
distributionsMM/Gaussiandistribution.py
distributionsMM/Generaldistribution.py
distributionsMM/__init__.py
distributionsMM.egg-info/PKG-INFO
distributionsMM.egg-info/SOURCES.txt
distributionsMM.egg-info/dependency_links.txt
distributionsMM.egg-info/not-zip-safe
distributionsMM.egg-info/top_level.txt