Metadata-Version: 1.0
Name: distributionsMM
Version: 1.0
Summary: distributions Gaussian and Binomial
Home-page: UNKNOWN
Author: MM
Author-email: UNKNOWN
License: UNKNOWN
Platform: UNKNOWN
